odoo8_addon_l10n_it_base_location_geonames_import-8.0.0.1.0.99.dev4-py2.7-nspkg.pth
odoo8_addon_l10n_it_base_location_geonames_import-8.0.0.1.0.99.dev4.dist-info/METADATA
odoo8_addon_l10n_it_base_location_geonames_import-8.0.0.1.0.99.dev4.dist-info/RECORD
odoo8_addon_l10n_it_base_location_geonames_import-8.0.0.1.0.99.dev4.dist-info/WHEEL
odoo8_addon_l10n_it_base_location_geonames_import-8.0.0.1.0.99.dev4.dist-info/namespace_packages.txt
odoo8_addon_l10n_it_base_location_geonames_import-8.0.0.1.0.99.dev4.dist-info/top_level.txt
odoo_addons/l10n_it_base_location_geonames_import/__init__.py
odoo_addons/l10n_it_base_location_geonames_import/__openerp__.py
odoo_addons/l10n_it_base_location_geonames_import/geonames_import.py
odoo_addons/l10n_it_base_location_geonames_import/i18n/it.po
odoo_addons/l10n_it_base_location_geonames_import/i18n/l10n_it_base_location_geonames_import.pot
odoo_addons/l10n_it_base_location_geonames_import/i18n/sl.po
odoo_addons/l10n_it_base_location_geonames_import/static/description/icon.png
odoo_addons/l10n_it_base_location_geonames_import/test/import.yml
